Metadata-Version: 2.1
Name: Adeepspeed
Version: 0.9.2
Summary: DeepSpeed library
Home-page: http://deepspeed.ai
Author: DeepSpeed Team
Author-email: deepspeed-info@microsoft.com
License: MIT
Project-URL: Documentation, https://deepspeed.readthedocs.io
Project-URL: Source, https://github.com/microsoft/DeepSpeed
Classifier: Programming Language :: Python :: 3.6
Classifier: Programming Language :: Python :: 3.7
Classifier: Programming Language :: Python :: 3.8
Classifier: Programming Language :: Python :: 3.9
Classifier: Programming Language :: Python :: 3.10
Provides-Extra: 1bit
Provides-Extra: 1bit_mpi
Provides-Extra: readthedocs
Provides-Extra: dev
Provides-Extra: autotuning
Provides-Extra: autotuning_ml
Provides-Extra: sparse_attn
Provides-Extra: inf
Provides-Extra: sd
Provides-Extra: all
License-File: LICENSE
